relayrl_framework-0.4.52.dist-info/METADATA
relayrl_framework-0.4.52.dist-info/WHEEL
relayrl_framework/__init__.py
relayrl_framework/relayrl_framework.cpython-39-darwin.so
relayrl_framework-0.4.52.dist-info/RECORD
