Metadata-Version: 2.4
Name: relayrl_framework
Version: 0.4.52
Summary: A system-oriented, distributed  reinforcement learning framework using a Rust backend with Python interfaces.
Keywords: reinforcement,learning,rl,distributed,system-integration
Author: jrcalgo <jacksonr121@outlook.com>
Author-email: jrcalgo <jacksonr121@outlook.com>
License: Apache-2.0
Project-URL: Source Code, https://github.com/jrcalgo/RelayRL-prototype
